addic7ed_cli-1.4.1.dist-info/metadata.json
addic7ed_cli-1.4.1.dist-info/DESCRIPTION.rst
addic7ed_cli-1.4.1.dist-info/METADATA
addic7ed_cli-1.4.1.dist-info/WHEEL
addic7ed_cli-1.4.1.dist-info/entry_points.txt
addic7ed_cli-1.4.1.dist-info/zip-safe
addic7ed_cli-1.4.1.dist-info/RECORD
addic7ed_cli-1.4.1.dist-info/top_level.txt
addic7ed_cli/__init__.py
addic7ed_cli/episode.py
addic7ed_cli/compat.py
addic7ed_cli/util.py
addic7ed_cli/language.py
addic7ed_cli/ui.py
addic7ed_cli/error.py
addic7ed_cli/request.py
addic7ed_cli/login.py
addic7ed_cli/version.py
