Metadata-Version: 2.0
Name: addic7ed-cli
Version: 1.4.1
Summary: A commandline access to addic7ed subtitles
Home-page: https://github.com/BenoitZugmeyer/addic7ed-cli/
Author: Benoît Zugmeyer
Author-email: bzugmeyer@gmail.com
License: Expat
Platform: UNKNOWN
Classifier: Development Status :: 5 - Production/Stable
Classifier: Environment :: Console
Classifier: Intended Audience :: End Users/Desktop
Classifier: License :: OSI Approved :: MIT License
Classifier: Operating System :: MacOS :: MacOS X
Classifier: Operating System :: POSIX
Classifier: Programming Language :: Python
Classifier: Programming Language :: Python :: 2.7
Classifier: Programming Language :: Python :: 3.3
Classifier: Programming Language :: Python :: 3.4
Classifier: Topic :: Multimedia
Requires-Dist: pyquery (>=1.2.4)
Requires-Dist: requests (>=2.2.1)
